CHANGELOG.rst
MANIFEST.in
README.rst
download_test_data.py
requirements.txt
setup.py
bidsify/__init__.py
bidsify/docker.py
bidsify/main.py
bidsify/mri2nifti.py
bidsify/phys2tsv.py
bidsify/utils.py
bidsify/version.py
bidsify.egg-info/PKG-INFO
bidsify.egg-info/SOURCES.txt
bidsify.egg-info/dependency_links.txt
bidsify.egg-info/entry_points.txt
bidsify.egg-info/requires.txt
bidsify.egg-info/top_level.txt
bidsify/data/dataset_description.json
bidsify/data/spinoza_cfg.yml
bidsify/data/spinoza_cfg_dicom.yml
bidsify/data/spinoza_metadata.yml
bidsify/tests/__init__.py
bidsify/tests/test_bidsify.py