Metadata-Version: 1.2
Name: bidsify
Version: 0.3.6
Summary: bidsify: Converts your (raw) data to the BIDS-format
Home-page: https://github.com/spinoza-rec/bidsify
Author: Lukas Snoek
Author-email: lukassnoek@gmail.com
Maintainer: Lukas Snoek
Maintainer-email: lukassnoek@gmail.com
License: 3-clause BSD
Platform: OS Independent
Classifier: Development Status :: 3 - Alpha
Classifier: Environment :: Console
Classifier: Intended Audience :: Science/Research
Classifier: License :: OSI Approved :: MIT License
Classifier: Operating System :: OS Independent
Classifier: Programming Language :: Python
Classifier: Topic :: Scientific/Engineering
Requires: numpy
